Workbook

Sheet 库存
A1: 采购 | B1: 发货 | C1: 产品 | D1: 单价 | E1: 运费 | F1: TEMU运费 | G1: 广告平均单价 | H1: 成本 (单个) | I1: 数量 | J1: 申报价 | K1: 净利率 | L1: 每单赚 | M1: 总价 | N1: 单个重量 (kg) | O1: 缩略图 | P1: SKC | Q1: 备注 | R1: =SUM(M:M) -> 116510.38
A2: 白色关节 | O2: =_xlfn.DISPIMG("ID_21FE4584230A4F61A119C46E1395D996",1) -> =DISPIMG("ID_21FE4584230A4F61A119C46E1395D996",1)
A3: 45475 | D3: 7.5 | E3: 2 | F3: 2.22 | H3: =D3+(E3/I3)+(F3/I3) -> 7.922 | I3: 10 | J3: 26 | K3: =(J3-H3)/J3 -> 0.69530769 | L3: =J3-H3 -> 18.078 | M3: =D3*I3+E3+F3 -> 79.22 | N3: 0.088 | Q3: 每个尺寸5个，有6个尺寸，总共30，加配件60个
A4: 45494 | B4: 45496 | D4: 7.5 | E4: 2 | F4: 3.43 | H4: =D4+(E4/I4)+(F4/I4) -> 8.043 | I4: 10 | J4: 20.8 | K4: =(J4-H4)/J4 -> 0.61331731 | L4: =J4-H4 -> 12.757 | M4: =D4*I4+E4+F4 -> 80.43
A5: 45504 | B5: 45509 | D5: 7.5 | E5: 3 | F5: 2 | H5: =D5+(E5/I5)+(F5/I5) -> 8 | I5: 10 | J5: 20.8 | K5: =(J5-H5)/J5 -> 0.61538462 | L5: =J5-H5 -> 12.8 | M5: =D5*I5+E5+F5 -> 80
A6: 45513 | B6: 45517 | D6: 7.5 | E6: 1 | F6: 14 | H6: =D6+(E6/I6)+(F6/I6) -> 8.75 | I6: 12 | J6: 20.8 | K6: =(J6-H6)/J6 -> 0.57932692 | L6: =J6-H6 -> 12.05 | M6: =D6*I6+E6+F6 -> 105
A7: 45513 | B7: 45520 | D7: 7.5 | E7: 1 | F7: 2 | H7: =D7+(E7/I7)+(F7/I7) -> 7.9285714 | I7: 7 | J7: 20.8 | K7: =(J7-H7)/J7 -> 0.61881868 | L7: =J7-H7 -> 12.871429 | M7: =D7*I7+E7+F7 -> 55.5
A8: 45519 | B8: 45521 | D8: 7.5 | E8: 2 | F8: 20.4 | H8: =D8+(E8/I8)+(F8/I8) -> 8.9 | I8: 16 | J8: 20.8 | K8: =(J8-H8)/J8 -> 0.57211538 | L8: =J8-H8 -> 11.9 | M8: =D8*I8+E8+F8 -> 142.4
A9: 45525 | B9: 45526 | D9: 7.5 | E9: 6 | F9: 20 | H9: =D9+(E9/I9)+(F9/I9) -> 8.8 | I9: 20 | J9: 20.8 | K9: =(J9-H9)/J9 -> 0.57692308 | L9: =J9-H9 -> 12 | M9: =D9*I9+E9+F9 -> 176
A10: 45527 | B10: 45529 | D10: 7.5 | E10: 3 | F10: 15 | H10: =D10+(E10/I10)+(F10/I10) -> 8.1206897 | I10: 29 | J10: 20.8 | K10: =(J10-H10)/J10 -> 0.60958223 | L10: =J10-H10 -> 12.67931 | M10: =D10*I10+E10+F10 -> 235.5
A11: 45527 | B11: 45533 | D11: 7.5 | E11: 3 | F11: 2.45 | H11: =D11+(E11/I11)+(F11/I11) -> 8.4083333 | I11: 6 | J11: 19.8 | K11: =(J11-H11)/J11 -> 0.5753367 | L11: =J11-H11 -> 11.391667 | M11: =D11*I11+E11+F11 -> 50.45
A12: 45533 | B12: 45535 | D12: 7.5 | E12: 3 | F12: 14.4 | H12: =D12+(E12/I12)+(F12/I12) -> 8.196 | I12: 25 | J12: 19.8 | K12: =(J12-H12)/J12 -> 0.58606061 | L12: =J12-H12 -> 11.604 | M12: =D12*I12+E12+F12 -> 204.9
A13: 45533 | B13: 45542 | D13: 7.5 | E13: 1.5 | F13: 3 | H13: =D13+(E13/I13)+(F13/I13) -> 7.95 | I13: 10 | J13: 19.8 | K13: =(J13-H13)/J13 -> 0.59848485 | L13: =J13-H13 -> 11.85 | M13: =D13*I13+E13+F13 -> 79.5
A14: 45533 | B14: 45544 | D14: 7.5 | E14: 1.5 | F14: 2 | H14: =D14+(E14/I14)+(F14/I14) -> 7.85 | I14: 10 | J14: 19.8 | K14: =(J14-H14)/J14 -> 0.60353535 | L14: =J14-H14 -> 11.95 | M14: =D14*I14+E14+F14 -> 78.5
A15: 45543 | B15: 45546 | D15: 7.5 | E15: 1 | F15: 3 | H15: =D15+(E15/I15)+(F15/I15) -> 7.7222222 | I15: 18 | J15: 19.8 | K15: =(J15-H15)/J15 -> 0.60998878 | L15: =J15-H15 -> 12.077778 | M15: =D15*I15+E15+F15 -> 139
... A23: 45562 | B23: 45568 | D23: 7.5 | E23: 3.5 | F23: 2 | H23: =D23+(E23/I23)+(F23/I23) -> 8.4166667 | I23: 6 | J23: 22.28 | K23: =(J23-H23)/J23 -> 0.6222322 | L23: =J23-H23 -> 13.863333 | M23: =D23*I23+E23+F23 -> 50.5
A24: 45565 | D24: 7.5 | E24: 6 | F24: 2 | H24: =D24+(E24/I24)+(F24/I24) -> 7.8478261 | I24: 23 | J24: 22.28 | K24: =(J24-H24)/J24 -> 0.64776364 | L24: =J24-H24 -> 14.432174 | M24: =D24*I24+E24+F24 -> 180.5
A25: 45565 | B25: 45580 | D25: 7.5 | E25: 6 | F25: 3 | H25: =D25+(E25/I25)+(F25/I25) -> 8.0294118 | I25: 17 | J25: 22.28 | K25: =(J25-H25)/J25 -> 0.63961348 | L25: =J25-H25 -> 14.250588 | M25: =D25*I25+E25+F25 -> 136.5
A26: 45572 | B26: 45583 | D26: 7.5 | E26: 3 | F26: 3.5 | H26: =D26+(E26/I26)+(F26/I26) -> 7.76 | I26: 25 | J26: 22.28 | K26: =(J26-H26)/J26 -> 0.65170557 | L26: =J26-H26 -> 14.52 | M26: =D26*I26+E26+F26 -> 194
A27: 45572 | B27: 45589 | D27: 7.5 | E27: 2 | F27: 3 | H27: =D27+(E27/I27)+(F27/I27) -> 7.7272727 | I27: 22 | J27: 22.28 | K27: =(J27-H27)/J27 -> 0.65317447 | L27: =J27-H27 -> 14.552727 | M27: =D27*I27+E27+F27 -> 170
A28: 45572 | B28: 45596 | D28: 7.5 | E28: 1 | F28: 0 | H28: =D28+(E28/I28)+(F28/I28) -> 7.8333333 | I28: 3 | J28: 22.28 | K28: =(J28-H28)/J28 -> 0.64841412 | L28: =J28-H28 -> 14.446667 | M28: =D28*I28+E28+F28 -> 23.5
A29: 45593 | B29: 45596 | D29: 7.5 | E29: 6 | F29: 4 | H29: =D29+(E29/I29)+(F29/I29) -> 7.8333333 | I29: 30 | J29: 22.28 | K29: =(J29-H29)/J29 -> 0.64841412 | L29: =J29-H29 -> 14.446667 | M29: =D29*I29+E29+F29 -> 235
A30: 45600 | B30: 45606 | D30: 7.5 | E30: 3 | F30: 4 | H30: =D30+(E30/I30)+(F30/I30) -> 7.7333333 | I30: 30 | J30: 22.28 | K30: =(J30-H30)/J30 -> 0.65290245 | L30: =J30-H30 -> 14.546667 | M30: =D30*I30+E30+F30 -> 232
A31: 45612 | B31: 45614 | D31: 7.5 | E31: 3 | F31: 4 | H31: =D31+(E31/I31)+(F31/I31) -> 7.7333333 | I31: 30 | J31: 20 | K31: =(J31-H31)/J31 -> 0.61333333 | L31: =J31-H31 -> 12.266667 | M31: =D31*I31+E31+F31 -> 232
A32: 45623 | B32: 45626 | D32: 7.5 | E32: 3 | F32: 3 | H32: =D32+(E32/I32)+(F32/I32) -> 7.8 | I32: 20 | J32: 20 | K32: =(J32-H32)/J32 -> 0.61 | L32: =J32-H32 -> 12.2 | M32: =D32*I32+E32+F32 -> 156
A33: 45628 | B33: 45632 | D33: 7.5 | E33: 2 | F33: 3.5 | H33: =D33+(E33/I33)+(F33/I33) -> 7.8666667 | I33: 15 | J33: 20 | K33: =(J33-H33)/J33 -> 0.60666667 | L33: =J33-H33 -> 12.133333 | M33: =D33*I33+E33+F33 -> 118
A34: 45631 | B34: 45633 | D34: 7.5 | E34: 6 | F34: 3 | H34: =D34+(E34/I34)+(F34/I34) -> 7.9090909 | I34: 22 | J34: 20 | K34: =(J34-H34)/J34 -> 0.60454545 | L34: =J34-H34 -> 12.090909 | M34: =D34*I34+E34+F34 -> 174
A35: 45631 | B35: 45638 | D35: 7.5 | E35: 0 | F35: 3 | H35: =D35+(E35/I35)+(F35/I35) -> 8.5 | I35: 3 | J35: 20 | K35: =(J35-H35)/J35 -> 0.575 | L35: =J35-H35 -> 11.5 | M35: =D35*I35+E35+F35 -> 25.5
A36: 45635 | D36: 7.5 | E36: 1.5 | H36: =D36+(E36/I36)+(F36/I36) -> 7.55 | I36: 30 | J36: 20 | K36: =(J36-H36)/J36 -> 0.6225 | L36: =J36-H36 -> 12.45 | M36: =D36*I36+E36+F36 -> 226.5
A37: 45639 | B37: 45641 | D37: 7.5 | E37: 3 | F37: 3 | H37: =D37+(E37/I37)+(F37/I37) -> 7.65 | I37: 40 | J37: 20 | K37: =(J37-H37)/J37 -> 0.6175 | L37: =J37-H37 -> 12.35 | M37: =D37*I37+E37+F37 -> 306 | Q37: 分2个备货单发出
A38: 45641 | B38: 45644 | D38: 7.5 | E38: 3 | F38: 7.6 | H38: =D38+(E38/I38)+(F38/I38) -> 7.8028571 | I38: 35 | J38: 20 | K38: =(J38-H38)/J38 -> 0.60985714 | L38: =J38-H38 -> 12.197143 | M38: =D38*I38+E38+F38 -> 273.1
A39: 45641 | B39: 45644 | D39: 7.5 | E39: 6 | F39: 3 | H39: =D39+(E39/I39)+(F39/I39) -> 7.86 | I39: 25 | J39: 20 | K39: =(J39-H39)/J39 -> 0.607 | L39: =J39-H39 -> 12.14 | M39: =D39*I39+E39+F39 -> 196.5
A40: 45643 | B40: 45646 | D40: 7.5 | E40: 3 | F40: 3 | H40: =D40+(E40/I40)+(F40/I40) -> 7.7 | I40: 30 | J40: 20 | K40: =(J40-H40)/J40 -> 0.615 | L40: =J40-H40 -> 12.3 | M40: =D40*I40+E40+F40 -> 231 | Q40: 实发29个
A41: 45645 | B41: 45647 | D41: 7.5 | E41: 6 | F41: 10 | H41: =D41+(E41/I41)+(F41/I41) -> 7.7 | I41: 80 | J41: 20 | K41: =(J41-H41)/J41 -> 0.615 | L41: =J41-H41 -> 12.3 | M41: =D41*I41+E41+F41 -> 616
A42: 45655 | B42: 45658 | D42: 7.5 | E42: 2 | F42: 6 | H42: =D42+(E42/I42)+(F42/I42) -> 7.66 | I42: 50 | J42: 20 | K42: =(J42-H42)/J42 -> 0.617 | L42: =J42-H42 -> 12.34 | M42: =D42*I42+E42+F42 -> 383
A43: 45658 | B43: 45662 | D43: 7.5 | E43: 2 | F43: 13 | H43: =D43+(E43/I43)+(F43/I43) -> 7.625 | I43: 120 | J43: 20 | K43: =(J43-H43)/J43 -> 0.61875 | L43: =J43-H43 -> 12.375 | M43: =D43*I43+E43+F43 -> 915
A44: 45664 | B44: 45668 | D44: 7.5 | E44: 6 | F44: 7 | H44: =D44+(E44/I44)+(F44/I44) -> 7.63 | I44: 100 | J44: 20 | K44: =(J44-H44)/J44 -> 0.6185 | L44: =J44-H44 -> 12.37 | M44: =D44*I44+E44+F44 -> 763 | Q44: 剩5个
A45: 45674 | B45: 45676 | D45: 7.5 | E45: 6 | F45: 11 | H45: =D45+(E45/I45)+(F45/I45) -> 7.6619048 | I45: 105 | J45: 20 | K45: =(J45-H45)/J45 -> 0.61690476 | L45: =J45-H45 -> 12.338095 | M45: =D45*I45+E45+F45 -> 804.5
A46: 45676 | B46: 45679 | D46: 7.5 | E46: 6 | F46: 8 | H46: =D46+(E46/I46)+(F46/I46) -> 7.7 | I46: 70 | J46: 20 | K46: =(J46-H46)/J46 -> 0.615 | L46: =J46-H46 -> 12.3 | M46: =D46*I46+E46+F46 -> 539
A47: 45693 | B47: 45696 | D47: 7.5 | E47: 0 | F47: 10.5 | H47: =D47+(E47/I47)+(F47/I47) -> 7.6166667 | I47: 90 | J47: 20 | K47: =(J47-H47)/J47 -> 0.61916667 | L47: =J47-H47 -> 12.383333 | M47: =D47*I47+E47+F47 -> 685.5
A48: 45693 | B48: 45699 | D48: 7.5 | E48: 0 | F48: 2 | H48: =D48+(E48/I48)+(F48/I48) -> 7.6818182 | I48: 11 | J48: 20 | K48: =(J48-H48)/J48 -> 0.61590909 | L48: =J48-H48 -> 12.318182 | M48: =D48*I48+E48+F48 -> 84.5
A49: 45698 | B49: 45703 | D49: 7.5 | E49: 3 | F49: 10.4 | H49: =D49+(E49/I49)+(F49/I49) -> 7.6488889 | I49: 90 | J49: 20 | K49: =(J49-H49)/J49 -> 0.61755556 | L49: =J49-H49 -> 12.351111 | M49: =D49*I49+E49+F49 -> 688.4
A50: 45700 | B50: 45702 | D50: 7.5 | E50: 3 | F50: 5.5 | H50: =D50+(E50/I50)+(F50/I50) -> 7.6416667 | I50: 60 | J50: 20 | K50: =(J50-H50)/J50 -> 0.61791667 | L50: =J50-H50 -> 12.358333 | M50: =D50*I50+E50+F50 -> 458.5
A51: 45707 | B51: 45710 | D51: 7.5 | E51: 4 | F51: 6 | H51: =D51+(E51/I51)+(F51/I51) -> 7.6666667 | I51: 60 | J51: 20 | K51: =(J51-H51)/J51 -> 0.61666667 | L51: =J51-H51 -> 12.333333 | M51: =D51*I51+E51+F51 -> 460
A52: 45707 | B52: 45715 | D52: 7.5 | E52: 4 | F52: 6.5 | H52: =D52+(E52/I52)+(F52/I52) -> 7.6810345 | I52: 58 | J52: 20 | K52: =(J52-H52)/J52 -> 0.61594828 | L52: =J52-H52 -> 12.318966 | M52: =D52*I52+E52+F52 -> 445.5
A53: 45714 | B53: 45717 | D53: 7.5 | E53: 3 | F53: 6 | H53: =D53+(E53/I53)+(F53/I53) -> 7.68 | I53: 50 | J53: 20 | K53: =(J53-H53)/J53 -> 0.616 | L53: =J53-H53 -> 12.32 | M53: =D53*I53+E53+F53 -> 384
A54: 45718 | B54: 45752 | D54: 7.5 | E54: 1 | F54: 5 | H54: =D54+(E54/I54)+(F54/I54) -> 7.9285714 | I54: 14 | J54: 20 | K54: =(J54-H54)/J54 -> 0.60357143 | L54: =J54-H54 -> 12.071429 | M54: =D54*I54+E54+F54 -> 111
A55: 45718 | B55: 45757 | D55: 7.5 | E55: 1 | F55: 2 | H55: =D55+(E55/I55)+(F55/I55) -> 7.7142857 | I55: 14 | J55: 20 | K55: =(J55-H55)/J55 -> 0.61428571 | L55: =J55-H55 -> 12.285714 | M55: =D55*I55+E55+F55 -> 108
A56: 45757 | B56: 45759 | D56: 7.5 | E56: 2 | F56: 3 | H56: =D56+(E56/I56)+(F56/I56) -> 7.8333333 | I56: 15 | J56: 20 | K56: =(J56-H56)/J56 -> 0.60833333 | L56: =J56-H56 -> 12.166667 | M56: =D56*I56+E56+F56 -> 117.5
... A97: 46018 | B97: 46021 | D97: 7.5 | E97: 0 | F97: 3 | H97: =D97+(E97/I97)+(F97/I97) -> 7.65 | I97: 20 | J97: 20 | K97: =(J97-H97)/J97 -> 0.6175 | L97: =J97-H97 -> 12.35 | M97: =D97*I97+E97+F97 -> 153
A98: 46018 | B98: 46023 | D98: 7.5 | E98: 0 | F98: 2 | H98: =D98+(E98/I98)+(F98/I98) -> 7.7 | I98: 10 | J98: 20 | K98: =(J98-H98)/J98 -> 0.615 | L98: =J98-H98 -> 12.3 | M98: =D98*I98+E98+F98 -> 77 | Q98: tk
A99: 46023 | B99: 46026 | D99: 7.5 | E99: 0 | F99: 3 | H99: =D99+(E99/I99)+(F99/I99) -> 7.6363636 | I99: 22 | J99: 20 | K99: =(J99-H99)/J99 -> 0.61818182 | L99: =J99-H99 -> 12.363636 | M99: =D99*I99+E99+F99 -> 168
A100: 46027 | B100: 46030 | D100: 7.5 | E100: 0 | F100: 3 | H100: =D100+(E100/I100)+(F100/I100) -> 7.6304348 | I100: 23 | J100: 20 | K100: =(J100-H100)/J100 -> 0.61847826 | L100: =J100-H100 -> 12.369565 | M100: =D100*I100+E100+F100 -> 175.5
A101: 46030 | B101: 46033 | D101: 7.5 | E101: 0 | F101: 3 | H101: =D101+(E101/I101)+(F101/I101) -> 7.5833333 | I101: 36 | J101: 20 | K101: =(J101-H101)/J101 -> 0.62083333 | L101: =J101-H101 -> 12.416667 | M101: =D101*I101+E101+F101 -> 273
A102: 46035 | B102: 46039 | D102: 7.5 | E102: 0 | F102: 3 | H102: =D102+(E102/I102)+(F102/I102) -> 7.6428571 | I102: 21 | J102: 20 | K102: =(J102-H102)/J102 -> 0.61785714 | L102: =J102-H102 -> 12.357143 | M102: =D102*I102+E102+F102 -> 160.5
A103: 46039 | B103: 46043 | D103: 7.5 | E103: 0 | F103: 2 | H103: =D103+(E103/I103)+(F103/I103) -> 7.6 | I103: 20 | J103: 20 | K103: =(J103-H103)/J103 -> 0.62 | L103: =J103-H103 -> 12.4 | M103: =D103*I103+E103+F103 -> 152
A104: 46046 | B104: 46051 | D104: 7.5 | E104: 0 | F104: 3 | H104: =D104+(E104/I104)+(F104/I104) -> 7.65 | I104: 20 | J104: 20 | K104: =(J104-H104)/J104 -> 0.6175 | L104: =J104-H104 -> 12.35 | M104: =D104*I104+E104+F104 -> 153
A105: 46052 | B105: 46056 | D105: 7.5 | E105: 0 | F105: 2 | H105: =D105+(E105/I105)+(F105/I105) -> 7.7 | I105: 10 | J105: 20 | K105: =(J105-H105)/J105 -> 0.615 | L105: =J105-H105 -> 12.3 | M105: =D105*I105+E105+F105 -> 77
A106: 46055 | B106: 46060 | D106: 7.5 | E106: 0 | F106: 5 | H106: =D106+(E106/I106)+(F106/I106) -> 7.6041667 | I106: 48 | J106: 20 | K106: =(J106-H106)/J106 -> 0.61979167 | L106: =J106-H106 -> 12.395833 | M106: =D106*I106+E106+F106 -> 365
A107: 46061 | B107: 46087 | D107: 7.5 | E107: 0 | F107: 2 | H107: =D107+(E107/I107)+(F107/I107) -> 7.5952381 | I107: 21 | J107: 20 | K107: =(J107-H107)/J107 -> 0.6202381 | L107: =J107-H107 -> 12.404762 | M107: =D107*I107+E107+F107 -> 159.5
A108: 46061 | B108: 46109 | D108: 7.5 | E108: 0 | F108: 2 | H108: =D108+(E108/I108)+(F108/I108) -> 7.8333333 | I108: 6 | J108: 20 | K108: =(J108-H108)/J108 -> 0.60833333 | L108: =J108-H108 -> 12.166667 | M108: =D108*I108+E108+F108 -> 47
A109: 46108 | B109: 46112 | D109: 7.5 | E109: 0 | F109: 3 | H109: =D109+(E109/I109)+(F109/I109) -> 7.6153846 | I109: 26 | J109: 20 | K109: =(J109-H109)/J109 -> 0.61923077 | L109: =J109-H109 -> 12.384615 | M109: =D109*I109+E109+F109 -> 198
A110: 46113 | B110: 46129 | D110: 7.5 | E110: 0 | F110: 2 | H110: =D110+(E110/I110)+(F110/I110) -> 7.6176471 | I110: 17 | J110: 20 | K110: =(J110-H110)/J110 -> 0.61911765 | L110: =J110-H110 -> 12.382353 | M110: =D110*I110+E110+F110 -> 129.5
A111: 46122 | B111: 46131 | D111: 7.5 | E111: 0 | F111: 2 | H111: =D111+(E111/I111)+(F111/I111) -> 7.625 | I111: 16 | J111: 20 | K111: =(J111-H111)/J111 -> 0.61875 | L111: =J111-H111 -> 12.375 | M111: =D111*I111+E111+F111 -> 122
A112: tk退供 | B112: 46136 | D112: 7.5 | E112: 0 | F112: 2 | H112: =D112+(E112/I112)+(F112/I112) -> 7.75 | I112: 8 | J112: 20 | K112: =(J112-H112)/J112 -> 0.6125 | L112: =J112-H112 -> 12.25 | M112: =D112*I112+E112+F112 -> 62
A113: 46135 | B113: 46138 | D113: 7.5 | E113: 0 | F113: 2 | H113: =D113+(E113/I113)+(F113/I113) -> 7.6428571 | I113: 14 | J113: 20 | K113: =(J113-H113)/J113 -> 0.61785714 | L113: =J113-H113 -> 12.357143 | M113: =D113*I113+E113+F113 -> 107
A114: 46162 | B114: 46173 | D114: 7.5 | E114: 0 | F114: 4 | H114: =D114+(E114/I114)+(F114/I114) -> 7.7 | I114: 20 | J114: 20 | K114: =(J114-H114)/J114 -> 0.615 | L114: =J114-H114 -> 12.3 | M114: =D114*I114+E114+F114 -> 154
A115: 46162 | B115: 46176 | D115: 7.5 | E115: 0 | F115: 3 | H115: =D115+(E115/I115)+(F115/I115) -> 7.7727273 | I115: 11 | J115: 20 | K115: =(J115-H115)/J115 -> 0.61136364 | L115: =J115-H115 -> 12.227273 | M115: =D115*I115+E115+F115 -> 85.5
A116: 46202 | B116: 46210 | D116: 7.5 | E116: 0 | F116: 3 | H116: =D116+(E116/I116)+(F116/I116) -> 7.7 | I116: 15 | J116: 20 | K116: =(J116-H116)/J116 -> 0.615 | L116: =J116-H116 -> 12.3 | M116: =D116*I116+E116+F116 -> 115.5
A117: 46218 | B117: 46218 | D117: 7.5 | E117: 0 | F117: 2 | H117: =D117+(E117/I117)+(F117/I117) -> 8.1666667 | I117: 3 | J117: 20 | K117: =(J117-H117)/J117 -> 0.59166667 | L117: =J117-H117 -> 11.833333 | M117: =D117*I117+E117+F117 -> 24.5
A118: 46218 | B118: 46221 | D118: 7.5 | E118: 0 | F118: 4 | H118: =D118+(E118/I118)+(F118/I118) -> 7.6666667 | I118: 24 | J118: 20 | K118: =(J118-H118)/J118 -> 0.61666667 | L118: =J118-H118 -> 12.333333 | M118: =D118*I118+E118+F118 -> 184
A119: 46230 | B119: 46232 | D119: 7.5 | E119: 0 | F119: 3 | H119: =D119+(E119/I119)+(F119/I119) -> 7.6153846 | I119: 26 | J119: 20 | K119: =(J119-H119)/J119 -> 0.61923077 | L119: =J119-H119 -> 12.384615 | M119: =D119*I119+E119+F119 -> 198
A120: 46234 | B120: 46238 | D120: 7.5 | E120: 0 | F120: 2 | H120: =D120+(E120/I120)+(F120/I120) -> 7.6 | I120: 20 | J120: 20 | K120: =(J120-H120)/J120 -> 0.62 | L120: =J120-H120 -> 12.4 | M120: =D120*I120+E120+F120 -> 152
A121: 46239 | B121: 46250 | D121: 7.5 | E121: 0 | F121: 2 | H121: =D121+(E121/I121)+(F121/I121) -> 7.6333333 | I121: 15 | J121: 20 | K121: =(J121-H121)/J121 -> 0.61833333 | L121: =J121-H121 -> 12.366667 | M121: =D121*I121+E121+F121 -> 114.5
A122: 46250 | B122: 46253 | D122: 7.5 | E122: 0 | F122: 3 | H122: =D122+(E122/I122)+(F122/I122) -> 7.6 | I122: 30 | J122: 20 | K122: =(J122-H122)/J122 -> 0.62 | L122: =J122-H122 -> 12.4 | M122: =D122*I122+E122+F122 -> 228
A123: 46253 | B123: 46256 | D123: 7.5 | E123: 0 | F123: 3 | H123: =D123+(E123/I123)+(F123/I123) -> 7.65 | I123: 20 | J123: 20 | K123: =(J123-H123)/J123 -> 0.6175 | L123: =J123-H123 -> 12.35 | M123: =D123*I123+E123+F123 -> 153
A124: 46267 | B124: 46270 | D124: 7.5 | E124: 0 | F124: 2 | H124: =D124+(E124/I124)+(F124/I124) -> 7.5666667 | I124: 30 | J124: 20 | K124: =(J124-H124)/J124 -> 0.62166667 | L124: =J124-H124 -> 12.433333 | M124: =D124*I124+E124+F124 -> 227
... A130: 46303 | B130: 46305 | D130: 7.5 | E130: 0 | F130: 2 | H130: =D130+(E130/I130)+(F130/I130) -> 7.58 | I130: 25 | J130: 20 | K130: =(J130-H130)/J130 -> 0.621 | L130: =J130-H130 -> 12.42 | M130: =D130*I130+E130+F130 -> 189.5
A131: 46313 | D131: 7.5 | E131: 0 | F131: 2 | H131: =D131+(E131/I131)+(F131/I131) -> 7.58 | I131: 25 | J131: 20 | K131: =(J131-H131)/J131 -> 0.621 | L131: =J131-H131 -> 12.42 | M131: =D131*I131+E131+F131 -> 189.5
A134: 新关节 | O134: =_xlfn.DISPIMG("ID_F472E8E4483746EEAB05049ADDC71A37",1) -> =DISPIMG("ID_F472E8E4483746EEAB05049ADDC71A37",1) | Q134: SKC：47044173701
A135: 45811 | B135: 45815 | D135: 7.5 | E135: 0 | F135: 3.5 | H135: =D135+(E135/I135)+(F135/I135) -> 8.0833333 | I135: 6 | J135: 22.77 | K135: =(J135-H135)/J135 -> 0.64500073 | L135: =J135-H135 -> 14.686667 | M135: =D135*I135+E135+F135 -> 48.5
A136: 45821 | B136: 45826 | D136: 7.5 | E136: 0 | F136: 2 | H136: =D136+(E136/I136)+(F136/I136) -> 7.9 | I136: 5 | J136: 22.77 | K136: =(J136-H136)/J136 -> 0.65305226 | L136: =J136-H136 -> 14.87 | M136: =D136*I136+E136+F136 -> 39.5
A137: 45821 | B137: 45828 | D137: 7.5 | E137: 0 | F137: 2 | H137: =D137+(E137/I137)+(F137/I137) -> 7.7 | I137: 10 | J137: 22.77 | K137: =(J137-H137)/J137 -> 0.66183575 | L137: =J137-H137 -> 15.07 | M137: =D137*I137+E137+F137 -> 77
A138: 45825 | B138: 45835 | D138: 7.5 | E138: 0 | F138: 2 | H138: =D138+(E138/I138)+(F138/I138) -> 7.7 | I138: 10 | J138: 22.77 | K138: =(J138-H138)/J138 -> 0.66183575 | L138: =J138-H138 -> 15.07 | M138: =D138*I138+E138+F138 -> 77
A139: 45825 | B139: 45838 | D139: 7.5 | E139: 0 | F139: 3 | H139: =D139+(E139/I139)+(F139/I139) -> 7.65 | I139: 20 | J139: 22.77 | K139: =(J139-H139)/J139 -> 0.66403162 | L139: =J139-H139 -> 15.12 | M139: =D139*I139+E139+F139 -> 153
A140: 45835 | B140: 45839 | D140: 7.5 | E140: 0 | F140: 2 | H140: =D140+(E140/I140)+(F140/I140) -> 7.6538462 | I140: 13 | J140: 22.77 | K140: =(J140-H140)/J140 -> 0.66386271 | L140: =J140-H140 -> 15.116154 | M140: =D140*I140+E140+F140 -> 99.5
A141: 45835 | B141: 45849 | D141: 7.5 | E141: 0 | F141: 2 | H141: =D141+(E141/I141)+(F141/I141) -> 7.8333333 | I141: 6 | J141: 22.77 | K141: =(J141-H141)/J141 -> 0.65598009 | L141: =J141-H141 -> 14.936667 | M141: =D141*I141+E141+F141 -> 47
A142: 45847 | B142: 45850 | D142: 7.5 | E142: 0 | F142: 3 | H142: =D142+(E142/I142)+(F142/I142) -> 7.8 | I142: 10 | J142: 22.77 | K142: =(J142-H142)/J142 -> 0.65744401 | L142: =J142-H142 -> 14.97 | M142: =D142*I142+E142+F142 -> 78
A143: 45851 | B143: 45855 | D143: 7.5 | E143: 0 | F143: 6 | H143: =D143+(E143/I143)+(F143/I143) -> 7.7857143 | I143: 21 | J143: 22.77 | K143: =(J143-H143)/J143 -> 0.6580714 | L143: =J143-H143 -> 14.984286 | M143: =D143*I143+E143+F143 -> 163.5
A144: 45851 | B144: 45857 | D144: 7.5 | E144: 0 | F144: 2 | H144: =D144+(E144/I144)+(F144/I144) -> 7.7 | I144: 10 | J144: 22.77 | K144: =(J144-H144)/J144 -> 0.66183575 | L144: =J144-H144 -> 15.07 | M144: =D144*I144+E144+F144 -> 77
A145: 45858 | B145: 45863 | D145: 7.5 | E145: 0 | F145: 3 | H145: =D145+(E145/I145)+(F145/I145) -> 7.7 | I145: 15 | J145: 22.77 | K145: =(J145-H145)/J145 -> 0.66183575 | L145: =J145-H145 -> 15.07 | M145: =D145*I145+E145+F145 -> 115.5
A146: 45862 | B146: 45868 | D146: 7.5 | E146: 0 | F146: 3 | H146: =D146+(E146/I146)+(F146/I146) -> 7.7 | I146: 15 | J146: 22.77 | K146: =(J146-H146)/J146 -> 0.66183575 | L146: =J146-H146 -> 15.07 | M146: =D146*I146+E146+F146 -> 115.5
... A170: 45994 | B170: 46004 | D170: 7.5 | E170: 0 | F170: 3 | H170: =D170+(E170/I170)+(F170/I170) -> 7.62 | I170: 25 | J170: 22.77 | K170: =(J170-H170)/J170 -> 0.66534914 | L170: =J170-H170 -> 15.15 | M170: =D170*I170+E170+F170 -> 190.5
A171: 46009 | B171: 46018 | D171: 7.5 | E171: 0 | F171: 3 | H171: 7.62 | I171: 20 | J171: 22.77 | K171: 0.619 | L171: 12.38 | M171: =D171*I171+E171+F171 -> 153
A172: 46023 | B172: 46025 | D172: 7.5 | E172: 0 | F172: 3 | H172: 7.62 | I172: 18 | J172: 22.77 | K172: 0.619 | L172: 12.38 | M172: =D172*I172+E172+F172 -> 138
A173: 46027 | B173: 46030 | D173: 7.5 | E173: 0 | F173: 3 | H173: 7.62 | I173: 17 | J173: 22.77 | K173: 0.619 | L173: 12.38 | M173: =D173*I173+E173+F173 -> 130.5
A174: 46030 | B174: 46034 | D174: 7.5 | E174: 0 | F174: 2 | H174: 7.62 | I174: 5 | J174: 22.77 | K174: 0.619 | L174: 12.38 | M174: =D174*I174+E174+F174 -> 39.5
A175: 46035 | B175: 46039 | D175: 7.5 | E175: 0 | F175: 3 | H175: 7.62 | I175: 19 | J175: 22.77 | K175: 0.619 | L175: 12.38 | M175: =D175*I175+E175+F175 -> 145.5
A176: 46039 | B176: 46046 | D176: 7.5 | E176: 0 | F176: 3 | H176: 7.62 | I176: 16 | J176: 22.77 | K176: 0.619 | L176: 12.38 | M176: =D176*I176+E176+F176 -> 123
A177: 46046 | B177: 46050 | D177: 7.5 | E177: 0 | F177: 3 | H177: 7.62 | I177: 24 | J177: 22.77 | K177: 0.619 | L177: 12.38 | M177: =D177*I177+E177+F177 -> 183
...

Sheet Y2
A1: 订单日期 | B1: 产品名 | C1: 采购价 | D1: 申报价 | E1: 活动价 | F1: 重量kg | G1: 国内快递 | H1: Y2头程 | I1: 操作贴单 | J1: 尾程运费 | K1: 平台补贴 | L1: 成本价 | M1: 每单赚 | N1: 毛利率 | P1: 头程/kg | Q1: 操作+贴单 | R1: 汇率
A2: 45826 | B2: 关节 | C2: 7.5 | D2: 99.33 | E2: 94.35 | F2: 0.0985 | G2: 5.3 | H2: =$P$2*F2 -> 7.092 | I2: =$Q$2 -> 5 | J2: =3.5*$R$2 -> 23.8 | L2: =C2+G2+H2+I2+J2 -> 48.692 | M2: =D2-L2 -> 50.638 | N2: =(M2-L2)/M2 -> 0.038429638 | P2: 72 | Q2: 5 | R2: 6.8
A3: 45826 | B3: 关节 | C3: 7.5 | D3: 99.33 | E3: 94.35 | F3: 0.0985 | G3: 5.3 | H3: =$P$2*F3 -> 7.092 | I3: =$Q$2 -> 5 | J3: =3.5*$R$2 -> 23.8 | L3: =C3+G3+H3+I3+J3 -> 48.692 | M3: =D3-L3 -> 50.638 | N3: =(M3-L3)/M3 -> 0.038429638
B4: 挂绳 | C4: =0.62*5 -> 3.1 | D4: 39 | E4: =D4*0.85 -> 33.15 | F4: 0.02 | H4: =$P$2*F4 -> 1.44 | I4: =$Q$2 -> 5 | J4: =2.5*$R$2 -> 17 | L4: =C4+G4+H4+I4+J4 -> 26.54 | M4: =D4-L4 -> 12.46

Sheet 物料
A1: 日期 | B1: 名称 | C1: 费用 | D1: =SUM(C:C) -> 2176.1 | BS1: 日期 | BT1: 15 | BU1: 13 | BV1: 11 | BW1: 8
A2: 45444 | B2: 标签纸 | C2: 7.5 | BT2: 2000 | BU2: 1000
A3: 45462 | B3: 快递包装袋 | C3: 11 | BS3: 45504 | BT3: 1000 | BV3: =-(SUMIFS(库存!M:M,库存!A:A,">="&DATE(YEAR(BS3),MONTH(BS3),1),库存!A:A,"<="&EOMONTH(BS3,0))+SUMIFS(物料!C:C,物料!A:A,">="&DATE(YEAR(BS3),MONTH(BS3),1),物料!A:A,"<="&EOMONTH(BS3,0))) -> -1121.29 | BW3: =SUM(BT4+BU4+BV3) -> 1478.71
A4: 45502 | B4: 标签纸 | C4: 6.4 | BS4: 45900 | BT4: 2600 | BV4: =-(SUMIFS(库存!M:M,库存!A:A,">="&DATE(YEAR(BS4),MONTH(BS4),1),库存!A:A,"<="&EOMONTH(BS4,0))+SUMIFS(物料!C:C,物料!A:A,">="&DATE(YEAR(BS4),MONTH(BS4),1),物料!A:A,"<="&EOMONTH(BS4,0))) -> -5542.88 | BW4: =SUM(BT5+BU5+BV4) -> 457.12
A5: 45508 | B5: 胶带 | C5: 6.9 | BS5: 45565 | BT5: 6000 | BV5: =-(SUMIFS(库存!M:M,库存!A:A,">="&DATE(YEAR(BS5),MONTH(BS5),1),库存!A:A,"<="&EOMONTH(BS5,0))+SUMIFS(物料!C:C,物料!A:A,">="&DATE(YEAR(BS5),MONTH(BS5),1),物料!A:A,"<="&EOMONTH(BS5,0))) -> -3632.195 | BW5: =SUM(BT6+BU6+BV5) -> 3767.805
A6: 45521 | B6: 快递袋 | C6: 6.4 | BS6: 45596 | BT6: 7400 | BV6: =-(SUMIFS(库存!M:M,库存!A:A,">="&DATE(YEAR(BS6),MONTH(BS6),1),库存!A:A,"<="&EOMONTH(BS6,0))+SUMIFS(物料!C:C,物料!A:A,">="&DATE(YEAR(BS6),MONTH(BS6),1),物料!A:A,"<="&EOMONTH(BS6,0))) -> -3160.2 | BW6: =SUM(BT7+BU7+BV6) -> 3839.8
A7: 45537 | B7: 标签纸 | C7: 4.5 | BS7: 45626 | BT7: 7000 | BV7: =-(SUMIFS(库存!M:M,库存!A:A,">="&DATE(YEAR(BS7),MONTH(BS7),1),库存!A:A,"<="&EOMONTH(BS7,0))+SUMIFS(物料!C:C,物料!A:A,">="&DATE(YEAR(BS7),MONTH(BS7),1),物料!A:A,"<="&EOMONTH(BS7,0))) -> -3057.8 | BW7: =SUM(BT8+BU8+BV7) -> 3442.2
A8: 45548 | B8: pe自封袋 | C8: 8.4 | BS8: 45657 | BT8: 6500 | BV8: =-(SUMIFS(库存!M:M,库存!A:A,">="&DATE(YEAR(BS8),MONTH(BS8),1),库存!A:A,"<="&EOMONTH(BS8,0))+SUMIFS(物料!C:C,物料!A:A,">="&DATE(YEAR(BS8),MONTH(BS8),1),物料!A:A,"<="&EOMONTH(BS8,0))) -> -6126.35 | BW8: =SUM(BT9+BU9+BV8) -> 5873.65
A9: 45555 | B9: opp自粘袋 | C9: 7.6 | BS9: 45688 | BT9: 12000 | BV9: =-(SUMIFS(库存!M:M,库存!A:A,">="&DATE(YEAR(BS9),MONTH(BS9),1),库存!A:A,"<="&EOMONTH(BS9,0))+SUMIFS(物料!C:C,物料!A:A,">="&DATE(YEAR(BS9),MONTH(BS9),1),物料!A:A,"<="&EOMONTH(BS9,0))) -> -9195.65 | BW9: =SUM(BT10+BU10+BV9) -> 5504.35
A10: 45559 | B10: 标签纸 | C10: 4.2 | BS10: 45716 | BT10: 14700 | BV10: =-(SUMIFS(库存!M:M,库存!A:A,">="&DATE(YEAR(BS10),MONTH(BS10),1),库存!A:A,"<="&EOMONTH(BS10,0))+SUMIFS(物料!C:C,物料!A:A,">="&DATE(YEAR(BS10),MONTH(BS10),1),物料!A:A,"<="&EOMONTH(BS10,0))) -> -10693.63 | BW10: =SUM(BT11+BU11+BV10) -> 7706.37
A11: 45582 | B11: 胶带 | C11: 5 | BS11: 45747 | BT11: 18400 | BV11: =-(SUMIFS(库存!M:M,库存!A:A,">="&DATE(YEAR(BS11),MONTH(BS11),1),库存!A:A,"<="&EOMONTH(BS11,0))+SUMIFS(物料!C:C,物料!A:A,">="&DATE(YEAR(BS11),MONTH(BS11),1),物料!A:A,"<="&EOMONTH(BS11,0))) -> -6083.44 | BW11: =SUM(BT12+BU12+BV11) -> 8916.56
A12: 45587 | B12: 标签纸 | C12: 4.8 | BS12: 45777 | BT12: 15000 | BV12: =-(SUMIFS(库存!M:M,库存!A:A,">="&DATE(YEAR(BS12),MONTH(BS12),1),库存!A:A,"<="&EOMONTH(BS12,0))+SUMIFS(物料!C:C,物料!A:A,">="&DATE(YEAR(BS12),MONTH(BS12),1),物料!A:A,"<="&EOMONTH(BS12,0))) -> -4839.7 | BW12: =SUM(BT13+BU13+BV12) -> 6360.3
A13: 45601 | B13: 珠光袋 | C13: 13 | BS13: 45808 | BT13: 11200 | BV13: =-(SUMIFS(库存!M:M,库存!A:A,">="&DATE(YEAR(BS13),MONTH(BS13),1),库存!A:A,"<="&EOMONTH(BS13,0))+SUMIFS(物料!C:C,物料!A:A,">="&DATE(YEAR(BS13),MONTH(BS13),1),物料!A:A,"<="&EOMONTH(BS13,0))) -> -4798.84 | BW13: =SUM(BT14+BU14+BV13) -> 4701.16
A14: 45603 | B14: 热敏打印机 | C14: 450 | BS14: 45838 | BT14: 9500 | BV14: =-(SUMIFS(库存!M:M,库存!A:A,">="&DATE(YEAR(BS14),MONTH(BS14),1),库存!A:A,"<="&EOMONTH(BS14,0))+SUMIFS(物料!C:C,物料!A:A,">="&DATE(YEAR(BS14),MONTH(BS14),1),物料!A:A,"<="&EOMONTH(BS14,0))) -> -5520.24 | BW14: =SUM(BT15+BU15+BV14) -> 6079.76
A15: 45610 | B15: 旧打印机转让 | C15: -190 | BS15: 45869 | BT15: 11600 | BV15: =-(SUMIFS(库存!M:M,库存!A:A,">="&DATE(YEAR(BS15),MONTH(BS15),1),库存!A:A,"<="&EOMONTH(BS15,0))+SUMIFS(物料!C:C,物料!A:A,">="&DATE(YEAR(BS15),MONTH(BS15),1),物料!A:A,"<="&EOMONTH(BS15,0))) -> -6505.94 | BW15: =SUM(BT16+BU16+BV15) -> 6994.06
A16: 45624 | B16: 快递费 | C16: 13 | BS16: 45898 | BT16: 13000 | BU16: 500 | BV16: =-(SUMIFS(库存!M:M,库存!A:A,">="&DATE(YEAR(BS16),MONTH(BS16),1),库存!A:A,"<="&EOMONTH(BS16,0))+SUMIFS(物料!C:C,物料!A:A,">="&DATE(YEAR(BS16),MONTH(BS16),1),物料!A:A,"<="&EOMONTH(BS16,0))) -> -5542.88 | BW16: =SUM(BT17+BU17+BV16) -> 5957.12
A17: 45632 | B17: 标签纸 | C17: 7.8 | BS17: 45930 | BT17: 9900 | BU17: 1600 | BV17: =-(SUMIFS(库存!M:M,库存!A:A,">="&DATE(YEAR(BS17),MONTH(BS17),1),库存!A:A,"<="&EOMONTH(BS17,0))+SUMIFS(物料!C:C,物料!A:A,">="&DATE(YEAR(BS17),MONTH(BS17),1),物料!A:A,"<="&EOMONTH(BS17,0))) -> -4907.52 | BW17: =SUM(BT18+BU18+BV17) -> 4592.48
A18: 45635 | B18: 快递费 | C18: 7.8 | BS18: 45961 | BT18: 7500 | BU18: 2000 | BV18: =-(SUMIFS(库存!M:M,库存!A:A,">="&DATE(YEAR(BS18),MONTH(BS18),1),库存!A:A,"<="&EOMONTH(BS18,0))+SUMIFS(物料!C:C,物料!A:A,">="&DATE(YEAR(BS18),MONTH(BS18),1),物料!A:A,"<="&EOMONTH(BS18,0))) -> -4272 | BW18: =SUM(BT19+BU19+BV18) -> 6528
A19: 45635 | B19: 商家助手(Temu版) | C19: 10 | BS19: 45991 | BT19: 9300 | BU19: 1500 | BV19: =-(SUMIFS(库存!M:M,库存!A:A,">="&DATE(YEAR(BS19),MONTH(BS19),1),库存!A:A,"<="&EOMONTH(BS19,0))+SUMIFS(物料!C:C,物料!A:A,">="&DATE(YEAR(BS19),MONTH(BS19),1),物料!A:A,"<="&EOMONTH(BS19,0))) -> -6382.26 | BW19: =SUM(BT20+BU20+BV19) -> 5117.74
A20: 45644 | B20: 快递袋 | C20: 16.6 | BS20: 46022 | BT20: 10400 | BU20: 1100 | BV20: =-(SUMIFS(库存!M:M,库存!A:A,">="&DATE(YEAR(BS20),MONTH(BS20),1),库存!A:A,"<="&EOMONTH(BS20,0))+SUMIFS(物料!C:C,物料!A:A,">="&DATE(YEAR(BS20),MONTH(BS20),1),物料!A:A,"<="&EOMONTH(BS20,0))) -> -3991.78 | BW20: =SUM(BT21+BU21+BV20) -> 8408.22
A21: 45648 | B21: 胶带 | C21: 12.2 | BS21: 46053 | BT21: 11000 | BU21: 1400 | BV21: =-(SUMIFS(库存!M:M,库存!A:A,">="&DATE(YEAR(BS21),MONTH(BS21),1),库存!A:A,"<="&EOMONTH(BS21,0))+SUMIFS(物料!C:C,物料!A:A,">="&DATE(YEAR(BS21),MONTH(BS21),1),物料!A:A,"<="&EOMONTH(BS21,0))) -> -5734.42 | BW21: =SUM(BT22+BU22+BV21) -> 4065.58
A22: 45650 | B22: 检测费 | C22: 150 | BS22: 46081 | BT22: 8800 | BU22: 1000 | BV22: =-(SUMIFS(库存!M:M,库存!A:A,">="&DATE(YEAR(BS22),MONTH(BS22),1),库存!A:A,"<="&EOMONTH(BS22,0))+SUMIFS(物料!C:C,物料!A:A,">="&DATE(YEAR(BS22),MONTH(BS22),1),物料!A:A,"<="&EOMONTH(BS22,0))) -> -3612.84 | BW22: =SUM(BT23+BU23+BV22) -> 6187.16
A23: 45650 | B23: opp自粘袋 | C23: 9 | BS23: 46112 | BT23: 8600 | BU23: 1200 | BV23: =-(SUMIFS(库存!M:M,库存!A:A,">="&DATE(YEAR(BS23),MONTH(BS23),1),库存!A:A,"<="&EOMONTH(BS23,0))+SUMIFS(物料!C:C,物料!A:A,">="&DATE(YEAR(BS23),MONTH(BS23),1),物料!A:A,"<="&EOMONTH(BS23,0))) -> -2897.24 | BW23: =SUM(BT24+BU24+BV23) -> 5002.76
A24: 46021 | B24: 标签纸 | C24: 3 | BS24: 46139 | BT24: 7100 | BU24: 800 | BV24: =-(SUMIFS(库存!M:M,库存!A:A,">="&DATE(YEAR(BS24),MONTH(BS24),1),库存!A:A,"<="&EOMONTH(BS24,0))+SUMIFS(物料!C:C,物料!A:A,">="&DATE(YEAR(BS24),MONTH(BS24),1),物料!A:A,"<="&EOMONTH(BS24,0))) -> -1552.86 | BW24: =SUM(BT25+BU25+BV24) -> 4047.14
A25: 45664 | B25: 标签纸 | C25: 7 | BS25: 46173 | BT25: 5100 | BU25: 500 | BV25: =-(SUMIFS(库存!M:M,库存!A:A,">="&DATE(YEAR(BS25),MONTH(BS25),1),库存!A:A,"<="&EOMONTH(BS25,0))+SUMIFS(物料!C:C,物料!A:A,">="&DATE(YEAR(BS25),MONTH(BS25),1),物料!A:A,"<="&EOMONTH(BS25,0))) -> -1804.6 | BW25: =SUM(BT26+BU26+BV25) -> 2595.4
A26: 45663 | B26: 编织袋 | C26: 11 | BS26: 46203 | BT26: 4000 | BU26: 400 | BV26: =-(SUMIFS(库存!M:M,库存!A:A,">="&DATE(YEAR(BS26),MONTH(BS26),1),库存!A:A,"<="&EOMONTH(BS26,0))+SUMIFS(物料!C:C,物料!A:A,">="&DATE(YEAR(BS26),MONTH(BS26),1),物料!A:A,"<="&EOMONTH(BS26,0))) -> -1697 | BW26: =SUM(BT27+BU27+BV26) -> 1603
A27: 45666 | B27: opp自粘袋 | C27: 8.5 | BS27: 46231 | BT27: 3300 | BU27: 0 | BV27: =-(SUMIFS(库存!M:M,库存!A:A,">="&DATE(YEAR(BS27),MONTH(BS27),1),库存!A:A,"<="&EOMONTH(BS27,0))+SUMIFS(物料!C:C,物料!A:A,">="&DATE(YEAR(BS27),MONTH(BS27),1),物料!A:A,"<="&EOMONTH(BS27,0))) -> -2310.7 | BW27: =SUM(BT28+BU28+BV27) -> 1712.3
... A29: 45674 | B29: 标签纸 | C29: 8 | BS29: 46295 | BT29: 4300 | BU29: 0 | BV29: =-(SUMIFS(库存!M:M,库存!A:A,">="&DATE(YEAR(BS29),MONTH(BS29),1),库存!A:A,"<="&EOMONTH(BS29,0))+SUMIFS(物料!C:C,物料!A:A,">="&DATE(YEAR(BS29),MONTH(BS29),1),物料!A:A,"<="&EOMONTH(BS29,0))) -> -1910.6 | BW29: =SUM(BT30+BU30+BV29) -> -1910.6
A30: 45711 | B30: 透明胶 | C30: 20
A31: 45717 | B31: 标签纸 | C31: 7
A32: 45726 | B32: 挂饰绳检测费 | C32: 80
A33: 45730 | B33: 标签纸 | C33: 13
A34: 45748 | B34: opp自粘袋 | C34: 6
A35: 45752 | B35: 快递袋 | C35: 4
A36: 45755 | B36: 土耳其代理 | C36: 20
A37: 45769 | B37: 标签纸 | C37: 4
A38: 45772 | B38: 欧代 | C38: 100
A39: 45805 | B39: 德国包装申报 | C39: 190
A40: 45806 | B40: 标签纸 | C40: 7
A41: 45818 | B41: 标签纸 | C41: 7
... A65: 46176 | B65: 德国包装申报 | C65: 190

Sheet 春节备货
A1: 产品名称 | B1: 最近7天 | C1: 最近30天 | D1: 仓内可用 | E1: 已发库存 | F1: 已采购 | G1: 卖家 发货天数 | H1: 物流天数 | I1: 入库时长 | J1: 预计可销售到 | K1: 剩余采购数量 7天销售 | L1: 剩余采购数量 30天销售 | M1: 单价 | N1: 总金额 | O1: 采购状态
A2: 挂绳 | B2: 82 | C2: 400 | D2: 313 | E2: 100 | F2: 400 | G2: 5 | H2: 2 | I2: 5 | J2: 46103 | K2: =(J2-TODAY()+G2+H2+I2)*(B2/7)-(D2+E2+F2) -> -3144.1429 | L2: =(J2-TODAY()+G2+H2+I2)*(C2/30)-(D2+E2+F2) -> -3466.3333 | M2: 1.86 | N2: =(K2+L2)/2*M2 -> -6147.7429 | O2: √
A3: 关节x3 | B3: 48 | C3: 219 | D3: 118 | E3: 98 | F3: 50 | G3: 2 | H3: 2 | I3: 5 | J3: 46091 | K3: =(J3-TODAY()+G3+H3+I3)*(B3/7)-(D3+E3+F3) -> -1733.4286 | L3: =(J3-TODAY()+G3+H3+I3)*(C3/30)-(D3+E3+F3) -> -1828.2 | M3: 7.5 | N3: =(K3+L3)/2*M3 -> -13356.107 | O3: √
A4: 玻璃刀-绿 | B4: 7 | C4: 24 | D4: 25 | E4: 0 | F4: 0 | G4: 3 | H4: 3 | I4: 5 | J4: 46091 | K4: =(J4-TODAY()+G4+H4+I4)*(B4/7)-(D4+E4+F4) -> -237 | L4: =(J4-TODAY()+G4+H4+I4)*(C4/30)-(D4+E4+F4) -> -194.6 | M4: 5.5 | N4: =(K4+L4)/2*M4 -> -1186.9
A5: 玻璃刀-红 | B5: 1 | C5: 7 | D5: 11 | E5: 0 | F5: 0 | G5: 3 | H5: 3 | I5: 5 | J5: 46091 | K5: =(J5-TODAY()+G5+H5+I5)*(B5/7)-(D5+E5+F5) -> -41.285714 | L5: =(J5-TODAY()+G5+H5+I5)*(C5/30)-(D5+E5+F5) -> -60.466667 | M5: 5.5 | N5: =(K5+L5)/2*M5 -> -279.81905
A6: 玻璃刀-蓝 | B6: 0 | C6: 5 | D6: 15 | E6: 0 | F6: 0 | G6: 3 | H6: 3 | I6: 5 | J6: 46091 | K6: =(J6-TODAY()+G6+H6+I6)*(B6/7)-(D6+E6+F6) -> -15 | L6: =(J6-TODAY()+G6+H6+I6)*(C6/30)-(D6+E6+F6) -> -50.333333 | M6: 3.3 | N6: =(K6+L6)/2*M6 -> -107.8
A7: 5色三角鼻 | B7: 19 | C7: 86 | D7: 43 | E7: 0 | F7: 0 | G7: 2 | H7: 2 | I7: 5 | J7: 46086 | K7: =(J7-TODAY()+G7+H7+I7)*(B7/7)-(D7+E7+F7) -> -637.42857 | L7: =(J7-TODAY()+G7+H7+I7)*(C7/30)-(D7+E7+F7) -> -670.8 | M7: 10 | N7: =(K7+L7)/2*M7 -> -6541.1429 | O7: √
A8: 睫毛眼睛 | B8: 8 | C8: 32 | D8: 11 | E8: 10 | F8: 0 | G8: 3 | H8: 3 | I8: 5 | J8: 46086 | K8: =(J8-TODAY()+G8+H8+I8)*(B8/7)-(D8+E8+F8) -> -269 | L8: =(J8-TODAY()+G8+H8+I8)*(C8/30)-(D8+E8+F8) -> -252.46667 | M8: 21.5 | N8: =(K8+L8)/2*M8 -> -5605.7667

Sheet TK
A1: 日期 | B1: 名称 | C1: 费用
A2: 45644

Sheet 成本
A1: 名称 | B1: 金额 | C1: =SUM(B:B) -> 2840
A2: 医社保 | B2: 1500
A3: 房租 | B3: 1000
A4: 水电 | B4: 300
A5: 三餐 | B5: 40
